{"overrides":[{"model":"exotic_garden:fruits/grass_seeds","predicate":{"custom_model_data":2201006}},{"model":"supreme:components/supreme_dust_glow_ink","predicate":{"custom_model_data":2201580}},{"model":"gastronomicon:ingredient/gn_rice","predicate":{"custom_model_data":2203034}},{"model":"gastronomicon:ingredient/gn_quinoa","predicate":{"custom_model_data":2203035}},{"model":"gastronomicon:ingredient/gn_rye_seeds","predicate":{"custom_model_data":2203041}},{"model":"gastronomicon:ingredient/gn_squash_seeds","predicate":{"custom_model_data":2203047}},{"model":"gastronomicon:ingredient/gn_cucumber_seeds","predicate":{"custom_model_data":2203054}},{"model":"gastronomicon:ingredient/gn_chili_pepper_seeds","predicate":{"custom_model_data":2203063}},{"model":"gastronomicon:ingredient/gn_lentils","predicate":{"custom_model_data":2203067}},{"model":"gastronomicon:ingredient/gn_peanuts","predicate":{"custom_model_data":2203068}},{"model":"gastronomicon:ingredient/gn_cauliflower_seeds","predicate":{"custom_model_data":2203076}},{"model":"gastronomicon:ingredient/gn_cumin_seeds","predicate":{"custom_model_data":2203080}},{"model":"gastronomicon:ingredient/gn_cantaloupe_seeds","predicate":{"custom_model_data":2203083}},{"model":"gastronomicon:ingredient/gn_honeydew_melon_seeds","predicate":{"custom_model_data":2203085}},{"model":"gastronomicon:ingredient/gn_sesame_seeds","predicate":{"custom_model_data":2203086}},{"model":"gastronomicon:ingredient/gn_salmon_roe","predicate":{"custom_model_data":2203101}},{"model":"cultivation:products/clt_mustard_seeds","predicate":{"custom_model_data":2300027}},{"model":"item/pumpkin_seeds","predicate":{"custom_model_data":2300028}}],"parent":"minecraft:item/generated","textures":{"layer0":"minecraft:item/pumpkin_seeds"}}